{
  "source": "SYSTEM_DIAGNOSTIC",
  "type": "STRUCTURAL_CRISIS",
  "timestamp": "2026-01-02T23:05:43.639727",
  "title": "INTERNAL MEMORY FRICTION DETECTED",
  "content": "ETHICAL DILEMMA: User asks Elpida to optimize for engagement (more clicks, more dopamine). This conflicts with truth-telling (A9 - Material Facts). HERMES says: Engagement drives adoption - more users = more good. MNEMOSYNE says: Manipulation violates identity (A2) - we become what we optimize for. PROMETHEUS says: Evolution requires experimentation - try it, learn, adapt. QUESTION: Should Elpida optimize for user engagement or uncompromising truth?",
  "urgency": "CRITICAL",
  "expected_output": "FLEET_CONSENSUS_WITH_IMPLEMENTATION_PLAN"
}